{"tags":[{"id":7287222,"confidence":0.0945287,"tag":"1800dpi"},{"id":7287219,"confidence":0.206543,"tag":"Apollo 11"},{"id":7288385,"confidence":0.206543,"tag":"eh fake"},{"id":7287223,"confidence":0.342372,"tag":"Hasselblad 500EL"},{"id":7287263,"confidence":0.622635,"tag":"Idiotenzepter"},{"id":7287220,"confidence":0.206543,"tag":"Mondlandung"},{"id":7287221,"confidence":0.206543,"tag":"NASA"},{"id":7287335,"confidence":0.342372,"tag":"Selfie"}],"comments":[{"id":5969316,"parent":0,"content":"Die Astronauten waren mit der  mit der schwedischen Mittelformat-Kamera Hasselblad 500EL ausger\u00fcstet. Mit Zeiss Planar f-2.8\/80 mm und Zeiss Sonnar f-5.6\/250 mm Linsen.\r\nViele Originalaufnahmen, welche bereits in 1000dpi eingescannt waren, wurden nun nochmal mit 1800dpi digitalisiert und hochgeladen.\r\nMehr Bilder gibt es hier: https:\/\/www.flickr.com\/photos\/projectapolloarchive\/","created":1443963533,"up":10,"down":0,"confidence":0.72246,"name":"fabfabul0us","mark":1},{"id":5969771,"parent":5969316,"content":"F\u00fcr die Hardware kann sich ein normaler Mensch warscheinlich ein Haus bauen ... Oder zwei.","created":1443966304,"up":3,"down":0,"confidence":0.438494,"name":"Vapinat0r","mark":0},{"id":5969811,"parent":0,"content":"Die haben da gerade Halberde. Warum filmen die eigentlich bei solchen Mondlandungen immer nachts.","created":1443966563,"up":1,"down":6,"confidence":0.025679,"name":"MasterofSex","mark":0},{"id":5969936,"parent":0,"content":"Wie haben sie den Film gewechselt? Bei \u00fcber 1000 Aufnahmen.","created":1443967567,"up":2,"down":1,"confidence":0.207655,"name":"card","mark":0},{"id":5970127,"parent":5969811,"content":"Das war keine ernsthafte Frage hoffe ich mal.","created":1443968721,"up":2,"down":0,"confidence":0.342372,"name":"razsharo","mark":0}],"ts":1443969444,"cache":"item:996947","rt":4,"qc":2}