{"tags":[{"id":7278074,"confidence":0.438494,"tag":"Adrian Borda"},{"id":7278518,"confidence":0.206543,"tag":"Cello"},{"id":7285994,"confidence":0.206543,"tag":"Dachboden^^"},{"id":7279244,"confidence":0.342372,"tag":"F-Loch"},{"id":7277995,"confidence":0.609657,"tag":"Geige"},{"id":7278494,"confidence":0.206543,"tag":"Geigenbauerporn"},{"id":7278436,"confidence":0.342372,"tag":"gr\u00f6\u00dfte Geige der Welt"},{"id":7278468,"confidence":0.206543,"tag":"Klangk\u00f6rper von innen"},{"id":7278025,"confidence":0.342372,"tag":"Licht"},{"id":7278341,"confidence":0.0455861,"tag":"Logo verkackt"},{"id":7278049,"confidence":0.856879,"tag":"Perspektive"},{"id":7278026,"confidence":0.342372,"tag":"Staub"},{"id":7282078,"confidence":0.206543,"tag":"Stimmstock fehlt"},{"id":7278017,"confidence":0.646114,"tag":"Violine"},{"id":7283061,"confidence":0.206543,"tag":"W\u00fcstenh\u00f6hle"}],"comments":[{"id":5960849,"parent":0,"content":"Was genau ist hier zu sehen?","created":1443887018,"up":3,"down":2,"confidence":0.23072,"name":"SinoTaurier","mark":0},{"id":5960863,"parent":5960849,"content":"Die Innenansicht einer Violine.","created":1443887133,"up":6,"down":0,"confidence":0.609657,"name":"WasisDalos","mark":9},{"id":5960877,"parent":5960863,"content":"Ganz sch\u00f6n staubig darin","created":1443887214,"up":1,"down":0,"confidence":0.206543,"name":"Critster","mark":1},{"id":5960941,"parent":5960877,"content":"[Mutterwitz]","created":1443887744,"up":30,"down":0,"confidence":0.886483,"name":"Kappa4","mark":0},{"id":5961086,"parent":0,"content":"Der Moment wenn du merkst, dass du versehentlich deine GoPr0 in deine Geige eingebaut hast","created":1443888832,"up":3,"down":15,"confidence":0.0583647,"name":"Vulkater","mark":0},{"id":5961090,"parent":5960863,"content":"Sicher, dass es eine Violine ist? Sieht f\u00fcr mich eher nach dem Innenleben eines Cellos aus...","created":1443888856,"up":3,"down":0,"confidence":0.438494,"name":"td9","mark":1},{"id":5961130,"parent":0,"content":"Warum genau f\u00e4llt es mir so schwer mir lediglich vorzustellen, dass das was ich hier sehe ziemlich klein und nicht zimmergro\u00df ist?","created":1443889128,"up":45,"down":0,"confidence":0.921346,"name":"mongobongo1810","mark":1},{"id":5961132,"parent":0,"content":"Da geht mein Instrumentenbauerherz auf.","created":1443889145,"up":6,"down":1,"confidence":0.486865,"name":"Kaikias","mark":1},{"id":5961184,"parent":0,"content":"Ist das gerendert ?","created":1443889509,"up":1,"down":0,"confidence":0.206543,"name":"Blondie","mark":0},{"id":5961227,"parent":5961086,"content":"Ein Satz, der mit \"Der Moment wenn du merkst\" beginnt kann nur Krebs verursachen.","created":1443889792,"up":6,"down":0,"confidence":0.609657,"name":"Baumwipfel","mark":0},{"id":5961278,"parent":5961132,"content":"Was baust du f\u00fcr Instrumente? Querbeet oder bestimmte?","created":1443890057,"up":1,"down":0,"confidence":0.206543,"name":"StepByStep","mark":0},{"id":5961322,"parent":5961278,"content":"Querbeet? Ist das auch eine Art Fl\u00f6te?","created":1443890379,"up":5,"down":1,"confidence":0.436491,"name":"MarvinKPR","mark":0},{"id":5961325,"parent":5961278,"content":"Ich bin Klavierbauergeselle.","created":1443890390,"up":7,"down":0,"confidence":0.645661,"name":"Kaikias","mark":1},{"id":5961381,"parent":5961130,"content":"Wegen der Tiefensch\u00e4rfe","created":1443890701,"up":1,"down":1,"confidence":0.0945287,"name":"affenpaste","mark":0},{"id":5961446,"parent":5961130,"content":"Wurde mit einer kleinen Blende fotografiert => die geringe Sch\u00e4rfentiefe fehlt, durch die man sofort erkannt h\u00e4tte, dass es sich um ein kleines Objekt handelt. Wenn sowohl Vordergrund als auch Hintergrund scharf sind, fehlt einfach der Eindruck als h\u00e4tte man ein kleines Objekt vor sich. \r\n\r\nOder anders herum geht es auch, so wie es die Telekom gemacht hat: Die haben aus der Luft Aufnahmen eines Hafens o.\u00e4. gemacht und dann eine geringe Sch\u00e4rfentiefe k\u00fcnstlich hinzugef\u00fcgt, d.h. sie haben das Bild oben und unten verschwommener gemacht. Dadurch sieht es aus als h\u00e4tte man eine Miniatur eines Hafens vor sich, obwohl es tats\u00e4chlich ein echter ist.","created":1443891037,"up":53,"down":1,"confidence":0.902283,"name":"Wrestler7","mark":0},{"id":5961566,"parent":5961132,"content":"mir schaudert es weil ich mir vorstelle, dass sie ein loch in die violine f\u00fcr dieses bild gebohrt haben.","created":1443891698,"up":1,"down":0,"confidence":0.206543,"name":"Dumbfuck","mark":0},{"id":5961573,"parent":0,"content":"Der Gedanke das in die Realit\u00e4t sprich in ein wirkliches Zimmer umzusetzen.... Der Geruch vom Holz und der Klang vom gehen aufm Boden... Ich w\u00fcrde vermutlich wirklich nie wieder raus wollen.","created":1443891721,"up":2,"down":0,"confidence":0.342372,"name":"Azzlack","mark":0},{"id":5961575,"parent":5961446,"content":"Ziemlich interessant! Vielen Dank f\u00fcr die Erkl\u00e4rung. Ich finds immer wieder erstaunlich wie schnell und einfach man hier Fachwissen findet.","created":1443891753,"up":22,"down":0,"confidence":0.85134,"name":"mongobongo1810","mark":1},{"id":5961711,"parent":5961446,"content":"Link zu besagten Bildern ?","created":1443892519,"up":4,"down":2,"confidence":0.299988,"name":"Gulaschsuppe","mark":0},{"id":5961733,"parent":5961446,"content":"Die entsprechend l\u00e4ngere Belichtungszeit sieht man auch an den Spuren der Staubteilchen.","created":1443892634,"up":4,"down":0,"confidence":0.5101,"name":"DontCare","mark":0},{"id":5961740,"parent":5961711,"content":"https:\/\/www.youtube.com\/watch?v=WxaY8fA7Xx0\r\n\r\nDie Technik nennt sich \"Tilt Shift\", falls jemand gr\u00f6\u00dferes Interesse daran hat.","created":1443892675,"up":4,"down":1,"confidence":0.375528,"name":"Wrestler7","mark":0},{"id":5961769,"parent":5961566,"content":"Wir haben mal ein Klavier angez\u00fcndet und so lange darauf gespielt bis es einfach nicht mehr ging. Und ein Bekannter von mir, der Holzblasinstrumentenmacher ist, tr\u00e4umt seit Jahren schon davon eine richtig teure Queer(beet)fl\u00f6te zu zerbrechen.","created":1443892820,"up":2,"down":1,"confidence":0.207655,"name":"Kaikias","mark":1},{"id":5961791,"parent":5961130,"content":"dachte zun\u00e4chst es sei eine grabkammer o.\u00e4.","created":1443892910,"up":1,"down":0,"confidence":0.206543,"name":"peterwackel","mark":0},{"id":5961875,"parent":0,"content":"Kann da nicht mal jemand eine Stadt reinshoppen? Hab da nicht so das Talent f\u00fcr. Besonders bei den Lichtverh\u00e4ltnissen stelle ich mir das schwer vor.","created":1443893438,"up":1,"down":0,"confidence":0.206543,"name":"pr0fessorbenis","mark":0},{"id":5962994,"parent":5961325,"content":"Du hast nicht zuf\u00e4llig Bilder die du zeigen k\u00f6nntest?","created":1443900142,"up":2,"down":0,"confidence":0.342372,"name":"StepByStep","mark":0},{"id":5963565,"parent":5961740,"content":"Tilt Shift != k\u00fcnstliche Unsch\u00e4rfe. K\u00fcnstlicher unsch\u00e4rfe markiert einfach nur ein paar Bereiche im Bild, die dann weichgezeichnet werden. Ein Tiltshiftobjektiv verschiebt die Bildebene und erreicht optische Unsch\u00e4rfe in verschiedenen Tiefenbereichen des Bildes. Au\u00dferdem kann man dadurch st\u00fczende Linien korrigieren. Das sieht sch\u00f6ner aus und kostet in der Produktion mehr.","created":1443903701,"up":2,"down":0,"confidence":0.342372,"name":"wh0thefuck","mark":0},{"id":5963694,"parent":5963565,"content":"Jopp, das ist richtig. Telekom hat den Tilt Shift Effekt aber simuliert und selbst dieses k\u00fcnstliche Tilt Shift wird meistens so genannt.","created":1443904318,"up":1,"down":0,"confidence":0.206543,"name":"Wrestler7","mark":0},{"id":5964299,"parent":0,"content":"Gem\u00fctlich...","created":1443908136,"up":1,"down":0,"confidence":0.206543,"name":"Afterausfluss","mark":1},{"id":5967484,"parent":5962994,"content":"Nein, leider nicht. Meine ganzen sch\u00f6nen Bilder sind mit der letzten Festplatte \u00fcber den Jordan gegangen. Aber ich kann zumindest die Funktionsweisen des Klaviers und von Fl\u00fcgeln erl\u00e4utern, wenn du magst. Einfach einen Schwerpunkt setzen und dann mache ich mal was.","created":1443953358,"up":1,"down":0,"confidence":0.206543,"name":"Kaikias","mark":1},{"id":5967822,"parent":5967484,"content":"Wenn du die Zeit und Lust hast, h\u00e4tte ich gerne gewusst, worin sich die zwei unterscheiden und die Funktionsweise d\u00fcrfte vermutlich doch fast gleich sein. Solltest du doch noch die M\u00f6glichkeit haben, Bilder zu machen, w\u00fcrde mich das auch freuen.","created":1443955481,"up":1,"down":0,"confidence":0.206543,"name":"StepByStep","mark":0}],"ts":1443969775,"cache":"item:995953","rt":7,"qc":2}